mort_jams/__init__.py
mort_jams/types.py
tests/__init__.py
tests/test_jams.py
mort_jams-1.12.0.dist-info/METADATA
mort_jams-1.12.0.dist-info/WHEEL
mort_jams-1.12.0.dist-info/top_level.txt
mort_jams-1.12.0.dist-info/RECORD
